rzw_mcp/__init__.py
rzw_mcp-0.1.0.dist-info/WHEEL
rzw_mcp-0.1.0.dist-info/entry_points.txt
rzw_mcp-0.1.0.dist-info/METADATA
rzw_mcp-0.1.0.dist-info/RECORD
