Metadata-Version: 2.3
Name: rzw-mcp
Version: 0.1.0
Summary: Add your description here
Author: renziwei
Author-email: renziwei <2510943025@qq.com>
Requires-Dist: mcp[cli]>=1.13.1
Requires-Python: >=3.13
